enkidu_ds/__init__.py
enkidu_ds/binary_tree.py
enkidu_ds-0.0.7.dist-info/METADATA
enkidu_ds-0.0.7.dist-info/WHEEL
enkidu_ds-0.0.7.dist-info/licenses/LICENSE
enkidu_ds-0.0.7.dist-info/RECORD
